pyaestro/__init__.py
pyaestro/abstracts/__init__.py
pyaestro/abstracts/graphs.py
pyaestro/abstracts/mpi.py
pyaestro/abstracts/scheduling.py
pyaestro/data/records.py
pyaestro/dataclasses/__init__.py
pyaestro/dataclasses/records.py
pyaestro/enums.py
pyaestro/interfaces/__init__.py
pyaestro/interfaces/mpi/__init__.py
pyaestro/interfaces/scheduling/__init__.py
pyaestro/interfaces/scheduling/localadapter.py
pyaestro/metaclasses.py
pyaestro/structures/__init__.py
pyaestro/structures/graphs.py
pyaestro/utilities/README.md
pyaestro/utilities/__init__.py
pyaestro/utilities/executor.py
pyaestro-0.0.1a2.dist-info/LICENSE
pyaestro-0.0.1a2.dist-info/WHEEL
pyaestro-0.0.1a2.dist-info/METADATA
pyaestro-0.0.1a2.dist-info/RECORD
